Perceptron/Perceptron.py
Perceptron/__init__.py
Perceptron/prepare.py
Perceptron/savemodel.py
Perceptron_techner3-0.0.2.dist-info/LICENSE
Perceptron_techner3-0.0.2.dist-info/METADATA
Perceptron_techner3-0.0.2.dist-info/WHEEL
Perceptron_techner3-0.0.2.dist-info/top_level.txt
Perceptron_techner3-0.0.2.dist-info/RECORD
